MANIFEST.in
README.rst
setup.py
spectrumwars/__init__.py
spectrumwars/game.py
spectrumwars/plotter.py
spectrumwars/rpc.py
spectrumwars/runner.py
spectrumwars/transceiver.py
spectrumwars.egg-info/PKG-INFO
spectrumwars.egg-info/SOURCES.txt
spectrumwars.egg-info/dependency_links.txt
spectrumwars.egg-info/entry_points.txt
spectrumwars.egg-info/requires.txt
spectrumwars.egg-info/top_level.txt
spectrumwars/sandbox/__init__.py
spectrumwars/sandbox/process.py
spectrumwars/sandbox/threaded.py
spectrumwars/testbed/__init__.py
spectrumwars/testbed/simulation.py
spectrumwars/testbed/usrp_sensing.py
spectrumwars/testbed/vesna.py
tests/__init__.py
tests/test_game.py
tests/test_radio.py
tests/test_sandbox.py
tests/test_simulation.py
tests/test_testbed.py
tests/test_transceiver.py
tests/test_usrp.py
tests/test_vesna.py