Metadata-Version: 1.1
Name: spectrumwars
Version: 0.0.6
Summary: A programming game where players compete for radio bandwidth.
Home-page: https://github.com/avian2/spectrumwars
Author: Tomaz Solc
Author-email: tomaz.solc@ijs.si
License: GPL3
Platform: UNKNOWN
Classifier: License :: OSI Approved :: GNU General Public License v3 or later (GPLv3+)
Classifier: Programming Language :: Python
Classifier: Programming Language :: Python :: 2
Classifier: Topic :: Games/Entertainment :: Simulation
Classifier: Topic :: Scientific/Engineering
